{"data_non_statistical":false,"goal_meta_link":"https://unstats.un.org/sdgs/metadata/files/Metadata-08-04-01.pdf ","goal_meta_link_text":"United Nations Sustainable Development Goals Metadata (PDF 4.0 MB)","graph_title":"Materijalni otisak, materijalni otisak po glavi stanovnika i materijalni otisak po BDP-u","graph_type":"line","indicator_number":"12.2.1","indicator_name":"Materijalni otisak, materijalni otisak po glavi stanovnika i materijalni otisak po BDP-u","indicator_sort_order":"12-02-01","published":true,"reporting_status":"notstarted","sdg_goal":"12","target_name":"global_targets.12-2-title","target_id":"12.2","un_custodian_agency":"United Nations Environment Programme (UNEP)","un_designated_tier":"3","page_content":"","national_metadata_update_url_text":"2023-09-04: see changes on GitHub","national_metadata_update_url":"https://github.com/sdgbih/sdg-data-bosnia/commit/b7bf7f7f6e566c5d18e48b4382dc0e8e31aa3f90","national_data_update_url_text":"2023-09-04: see changes on GitHub","national_data_update_url":"https://github.com/sdgbih/sdg-data-bosnia/commit/b7bf7f7f6e566c5d18e48b4382dc0e8e31aa3f90","indicator":"12.2.1"}