{"data_non_statistical":false,"goal_meta_link":"https://unstats.un.org/sdgs/tierIII-indicators/files/Tier3-16-07-02.pdf","goal_meta_link_text":"United Nations Sustainable Development Goals Tier 3 Work Plan (PDF 77.8 KB)","graph_title":"Udio stanovni\u0161tva koje vjeruje da je dono\u0161enje odluka inkluzivno i odgovorno, prema spolu, dobi, invaliditetu i skupini stanovni\u0161tva","graph_type":"line","indicator_number":"16.7.2","indicator_name":"Udio stanovni\u0161tva koje vjeruje da je dono\u0161enje odluka inkluzivno i odgovorno, prema spolu, dobi, invaliditetu i skupini stanovni\u0161tva","indicator_sort_order":"16-07-02","published":true,"reporting_status":"notstarted","sdg_goal":"16","target_name":"Osigurati odgovorno, uklju\u010divo, participativno i reprezentativno dono\u0161enje odluka na svim razinama","target_id":"16.7","un_custodian_agency":"United Nations Development Programme (UNDP)","un_designated_tier":"3","page_content":"","national_metadata_update_url_text":"2023-10-26: see changes on GitHub","national_metadata_update_url":"https://github.com/sdgbih/sdg-data-bosnia/commit/603c5b290dda38cc9e18d0140d389d098029023f","national_data_update_url_text":"2023-10-26: see changes on GitHub","national_data_update_url":"https://github.com/sdgbih/sdg-data-bosnia/commit/603c5b290dda38cc9e18d0140d389d098029023f","indicator":"16.7.2"}