[{"Year":2014,"Value":null,"UNIT_MEASURE":"TONNES","SERIES":"Electronic waste recycling (Tonnes)"},{"Year":2015,"Value":null,"UNIT_MEASURE":"TONNES","SERIES":"Electronic waste recycling (Tonnes)"},{"Year":2016,"Value":null,"UNIT_MEASURE":"TONNES","SERIES":"Electronic waste recycling (Tonnes)"},{"Year":2017,"Value":null,"UNIT_MEASURE":"TONNES","SERIES":"Electronic waste recycling (Tonnes)"},{"Year":2018,"Value":null,"UNIT_MEASURE":"TONNES","SERIES":"Electronic waste recycling (Tonnes)"},{"Year":2019,"Value":null,"UNIT_MEASURE":"TONNES","SERIES":"Electronic waste recycling (Tonnes)"},{"Year":2014,"Value":null,"UNIT_MEASURE":"Kilograms","SERIES":"Electronic waste recycling, per capita (Kg)"},{"Year":2015,"Value":null,"UNIT_MEASURE":"Kilograms","SERIES":"Electronic waste recycling, per capita (Kg)"},{"Year":2016,"Value":null,"UNIT_MEASURE":"Kilograms","SERIES":"Electronic waste recycling, per capita (Kg)"},{"Year":2017,"Value":null,"UNIT_MEASURE":"Kilograms","SERIES":"Electronic waste recycling, per capita (Kg)"},{"Year":2018,"Value":null,"UNIT_MEASURE":"Kilograms","SERIES":"Electronic waste recycling, per capita (Kg)"},{"Year":2019,"Value":null,"UNIT_MEASURE":"Kilograms","SERIES":"Electronic waste recycling, per capita (Kg)"},{"Year":2014,"Value":null,"UNIT_MEASURE":"Percent","SERIES":"Electronic waste recycling, rate (%)"}]