[{"Year":2000,"Value":5.19,"UNIT_MEASURE":"PT","SERIES":"NY_GDP_PCAP"},{"Year":2001,"Value":2.31,"UNIT_MEASURE":"PT","SERIES":"NY_GDP_PCAP"},{"Year":2002,"Value":4.92,"UNIT_MEASURE":"PT","SERIES":"NY_GDP_PCAP"},{"Year":2003,"Value":3.79,"UNIT_MEASURE":"PT","SERIES":"NY_GDP_PCAP"},{"Year":2004,"Value":6.27,"UNIT_MEASURE":"PT","SERIES":"NY_GDP_PCAP"},{"Year":2005,"Value":3.87,"UNIT_MEASURE":"PT","SERIES":"NY_GDP_PCAP"},{"Year":2006,"Value":5.41,"UNIT_MEASURE":"PT","SERIES":"NY_GDP_PCAP"},{"Year":2007,"Value":5.93,"UNIT_MEASURE":"PT","SERIES":"NY_GDP_PCAP"},{"Year":2008,"Value":5.68,"UNIT_MEASURE":"PT","SERIES":"NY_GDP_PCAP"},{"Year":2009,"Value":-2.53,"UNIT_MEASURE":"PT","SERIES":"NY_GDP_PCAP"},{"Year":2010,"Value":1.69,"UNIT_MEASURE":"PT","SERIES":"NY_GDP_PCAP"},{"Year":2011,"Value":2.18,"UNIT_MEASURE":"PT","SERIES":"NY_GDP_PCAP"},{"Year":2012,"Value":0.72,"UNIT_MEASURE":"PT","SERIES":"NY_GDP_PCAP"},{"Year":2013,"Value":4.15,"UNIT_MEASURE":"PT","SERIES":"NY_GDP_PCAP"},{"Year":2014,"Value":2.91,"UNIT_MEASURE":"PT","SERIES":"NY_GDP_PCAP"},{"Year":2015,"Value":4.67,"UNIT_MEASURE":"PT","SERIES":"NY_GDP_PCAP"},{"Year":2016,"Value":4.46,"UNIT_MEASURE":"PT","SERIES":"NY_GDP_PCAP"},{"Year":2017,"Value":4.24,"UNIT_MEASURE":"PT","SERIES":"NY_GDP_PCAP"},{"Year":2018,"Value":4.6,"UNIT_MEASURE":"PT","SERIES":"NY_GDP_PCAP"},{"Year":2019,"Value":3.55,"UNIT_MEASURE":"PT","SERIES":"NY_GDP_PCAP"}]